README.rst
setup.py
wok_code/.coveragerc
wok_code/LICENSE
wok_code/__init__.py
wok_code/__main__.py
wok_code/config_apache2.sh
wok_code/config_multiple_postgresql.py
wok_code/config_multiple_postgresql.sh
wok_code/do_gitignore.py
wok_code/do_set_utf8.py
wok_code/enable_postgresql.sh
wok_code/eval_gtin.py
wok_code/gen_addons_table.py
wok_code/install_pip2.sh
wok_code/install_python_3_from_source.sh
wok_code/pgconf.py
wok_code/please.man
wok_code/pre-commit
wok_code/rm_dir_with_space.py
wok_code/set_python_version
wok_code/ssh.py
wok_code/sub.sh
wok_code/to_oca.2p8
wok_code/to_pep8.2p8
wok_code/to_zero.2p8
wok_code.egg-info/PKG-INFO
wok_code.egg-info/SOURCES.txt
wok_code.egg-info/dependency_links.txt
wok_code.egg-info/entry_points.txt
wok_code.egg-info/not-zip-safe
wok_code.egg-info/requires.txt
wok_code.egg-info/top_level.txt
wok_code/docs/MAINPAGE.rst
wok_code/docs/Makefile
wok_code/docs/__init__.txt
wok_code/docs/conf.py
wok_code/docs/index.rst
wok_code/docs/logozero_180x46.png
wok_code/docs/readthedocs.yml
wok_code/docs/requirements.txt
wok_code/docs/rtd_automodule.rst
wok_code/docs/rtd_changelog.rst
wok_code/docs/rtd_credits.rst
wok_code/docs/rtd_description.rst
wok_code/docs/rtd_description_arcangelo.rst
wok_code/docs/rtd_description_gen_readme.rst
wok_code/docs/rtd_description_macro.rst
wok_code/docs/rtd_description_odoo_dependencies.rst
wok_code/docs/rtd_description_please.rst
wok_code/docs/rtd_getting_started.rst
wok_code/docs/rtd_usage.rst
wok_code/docs/rtd_usage_arcangelo.rst
wok_code/docs/rtd_usage_gen_readme.rst
wok_code/docs/rtd_usage_gen_readme_sym.rst
wok_code/docs/rtd_usage_odoo_dependencies.rst
wok_code/docs/rtd_usage_please.rst
wok_code/docs/_build/doctrees/index.doctree
wok_code/docs/_build/doctrees/rtd_description.doctree
wok_code/docs/_build/doctrees/rtd_macro.doctree
wok_code/docs/_build/doctrees/rtd_usage.doctree
wok_code/docs/_build/html/.buildinfo
wok_code/docs/_build/html/.nojekyll
wok_code/docs/_build/html/genindex.html
wok_code/docs/_build/html/index.html
wok_code/docs/_build/html/objects.inv
wok_code/docs/_build/html/rtd_description.html
wok_code/docs/_build/html/rtd_macro.html
wok_code/docs/_build/html/rtd_usage.html
wok_code/docs/_build/html/search.html
wok_code/egg-info/CHANGELOG.rst
wok_code/egg-info/DESCRIPTION.rst
wok_code/egg-info/USAGE.rst
wok_code/egg-info/__manifest__.rst
wok_code/egg-info/description_arcangelo.rst
wok_code/egg-info/description_gen_readme.rst
wok_code/egg-info/description_macro.csv
wok_code/egg-info/description_odoo_dependencies.rst
wok_code/egg-info/description_please.rst
wok_code/egg-info/odoo_migration_path.rst
wok_code/egg-info/rules_usage_arcangelo.csv
wok_code/egg-info/rules_usage_items.csv
wok_code/egg-info/usage_arcangelo.rst
wok_code/egg-info/usage_gen_readme.rst
wok_code/egg-info/usage_gen_readme_sym.csv
wok_code/egg-info/usage_odoo_dependencies.rst
wok_code/egg-info/usage_please.csv
