Metadata-Version: 2.1
Name: wok-code
Version: 2.0.23
Summary: Python developers tools
Home-page: https://github.com/zeroincombenze/tools
Author: Antonio Maria Vigliotti
Author-email: antoniomaria.vigliotti@gmail.com
License: GPL-3.0-or-later
Project-URL: Source, https://github.com/zeroincombenze/tools/tree/master/wok_code
Project-URL: Documentation, https://zeroincombenze-tools.readthedocs.io/en/latest/#zerobug
Project-URL: Changelog, https://github.com/zeroincombenze/tools/blob/master/wok_code/egg-info/CHANGELOG.rst
Keywords: linux odoo documentation development
Platform: UNKNOWN
Classifier: Development Status :: 4 - Beta
Classifier: Operating System :: POSIX
Classifier: Programming Language :: Python :: 2.7
Classifier: Programming Language :: Python :: 3.7
Classifier: Programming Language :: Python :: 3.8
Classifier: Programming Language :: Python :: 3.9
Classifier: Programming Language :: Python :: 3.10
Classifier: Intended Audience :: Developers
Classifier: Topic :: Software Development
Classifier: Topic :: Software Development :: Libraries
Classifier: Topic :: Software Development :: Build Tools
Classifier: Operating System :: OS Independent
